Metadata-Version: 1.1
Name: django-remote-image
Version: 0.1
Summary: Custom django form field for downloading images from a URL on a URLInput.
Home-page: https://github.com/LucasCTN/django-remote-image
Author: Lucas Nascimento
Author-email: lucascampostn@gmail.com
License: MIT License
Platform: UNKNOWN
Classifier: Environment :: Web Environment
Classifier: Framework :: Django
Classifier: Intended Audience :: Developers
Classifier: License :: OSI Approved :: MIT License
Classifier: Operating System :: OS Independent
Classifier: Programming Language :: Python
Classifier: Programming Language :: Python :: 3.5
Classifier: Programming Language :: Python :: 3.6
Classifier: Topic :: Internet :: WWW/HTTP
Classifier: Topic :: Internet :: WWW/HTTP :: Dynamic Content
